{"id":48,"idInBook":2057,"chapterId":11,"bookId":2,"arabic":"وَحَدَّثَنَا قُتَيْبَةُ بْنُ سَعِيدٍ، عَنْ مَالِكِ بْنِ أَنَسٍ، ح وَحَدَّثَنَا أَبُو الرَّبِيعِ الزَّهْرَانِيُّ، وَقُتَيْبَةُ، بْنُ سَعِيدٍ قَالاَ حَدَّثَنَا حَمَّادٌ، ح وَحَدَّثَنَا يَحْيَى بْنُ أَيُّوبَ، حَدَّثَنَا ابْنُ عُلَيَّةَ، كُلُّهُمْ عَنْ أَيُّوبَ، عَنْ مُحَمَّدٍ، عَنْ أُمِّ عَطِيَّةَ، قَالَتْ تُوُفِّيَتْ إِحْدَى بَنَاتِ النَّبِيِّ صلى الله عليه وسلم ‏.‏ وَفِي حَدِيثِ ابْنِ عُلَيَّةَ قَالَتْ أَتَانَا رَسُولُ اللَّهِ صلى الله عليه وسلم وَنَحْنُ نَغْسِلُ ابْنَتَهُ ‏.‏ وَفِي حَدِيثِ مَالِكٍ قَالَتْ دَخَلَ عَلَيْنَا رَسُولُ اللَّهِ صلى الله عليه وسلم حِينَ تُوُفِّيَتِ ابْنَتُهُ ‏.‏ بِمِثْلِ حَدِيثِ يَزِيدَ بْنِ زُرَيْعٍ عَنْ أَيُّوبَ عَنْ مُحَمَّدٍ عَنْ أُمِّ عَطِيَّةَ ‏.‏","english":{"narrator":"Umm 'Atiyya reported:","text":"One of the daughters of the Messenger of Allah (ﷺ) died. And in the hadith transmitted by Ibn 'Ulayya (the words are): The Messenger of Allah (ﷺ) came to us and we were washing his daughter. And in the hadith transmitted by Malik (the words are): There came in (our apartment) the Messenger of Allah (way peace be upon him) when his daughter died. The rest of the hadith is the same as narrated by Yazid b. Zurai' from Ayyub from Muhammad from Umm 'Atiyya."},"hadithNumber":2057,"hadithId":48,"reference":"11:48","meta":{"id":"muslim","length":7563,"totalChapters":57,"arabic":{"title":"صحيح مسلم","author":"الإمام مسلم بن الحجاج القشيري النيسابوري"},"english":{"title":"Sahih Muslim","author":"Imam Muslim ibn al-Hajjaj al-Naysaburi"}},"chapter":{"id":11,"bookId":2,"arabic":"كتاب الجنائز","english":"The Book of Prayer - Funerals","startHadith":2010,"endHadith":2147,"totalHadiths":138},"version":{"name":"muslim","title":"Sahih Muslim","chapters":57}}