{"id":17,"idInBook":4404,"chapterId":32,"bookId":2,"arabic":"حَدَّثَنَا مُحَمَّدُ بْنُ الْمُثَنَّى، وَعُبَيْدُ اللَّهِ بْنُ سَعِيدٍ، قَالاَ حَدَّثَنَا عَبْدُ الرَّحْمَنِ بْنُ مَهْدِيٍّ، عَنْ شُعْبَةَ، عَنْ ثَابِتٍ، عَنْ أَنَسٍ، قَالَ قَالَ رَسُولُ اللَّهِ صلى الله عليه وسلم ‏\n\"‏ لِكُلِّ غَادِرٍ لِوَاءٌ يَوْمَ الْقِيَامَةِ يُعْرَفُ بِهِ ‏\"‏ ‏.‏","english":{"narrator":"Anas reported Allah's Messenger (ﷺ) having said this:","text":"There would be a flag for every perfidious person on the Day of Judgment by which he will be recognised."},"hadithNumber":4404,"hadithId":17,"reference":"32:17","meta":{"id":"muslim","length":7563,"totalChapters":57,"arabic":{"title":"صحيح مسلم","author":"الإمام مسلم بن الحجاج القشيري النيسابوري"},"english":{"title":"Sahih Muslim","author":"Imam Muslim ibn al-Hajjaj al-Naysaburi"}},"chapter":{"id":32,"bookId":2,"arabic":"كتاب الجهاد والسير","english":"The Book of Jihad and Expeditions","startHadith":4388,"endHadith":4569,"totalHadiths":182},"version":{"name":"muslim","title":"Sahih Muslim","chapters":57}}