{"id":2,"idInBook":6851,"chapterId":51,"bookId":2,"arabic":"حَدَّثَنَا أَبُو بَكْرِ بْنُ أَبِي شَيْبَةَ، وَزُهَيْرُ بْنُ حَرْبٍ، وَأَحْمَدُ بْنُ عَبْدَةَ الضَّبِّيُّ، - وَاللَّفْظُ\n لاِبْنِ أَبِي شَيْبَةَ - قَالَ ابْنُ عَبْدَةَ أَخْبَرَنَا وَقَالَ الآخَرَانِ، حَدَّثَنَا سُفْيَانُ بْنُ عُيَيْنَةَ، عَنْ عَمْرٍو،\n أَنَّهُ سَمِعَ جَابِرًا، يَقُولُ أَتَى النَّبِيُّ صلى الله عليه وسلم قَبْرَ عَبْدِ اللَّهِ بْنِ أُبَىٍّ فَأَخْرَجَهُ مِنْ\n قَبْرِهِ فَوَضَعَهُ عَلَى رُكْبَتَيْهِ وَنَفَثَ عَلَيْهِ مِنْ رِيقِهِ وَأَلْبَسَهُ قَمِيصَهُ فَاللَّهُ أَعْلَمُ ‏.‏","english":{"narrator":"","text":"Jabir reported Allah's Apostle (ﷺ) came to the grave of 'Abdullah b. Ubayy, brought him out from that, placed him on his knee and put his saliva in his mouth and shrouded him in his own shirt and Allah knows best."},"hadithNumber":6851,"hadithId":2,"reference":"51:2","meta":{"id":"muslim","length":7563,"totalChapters":57,"arabic":{"title":"صحيح مسلم","author":"الإمام مسلم بن الحجاج القشيري النيسابوري"},"english":{"title":"Sahih Muslim","author":"Imam Muslim ibn al-Hajjaj al-Naysaburi"}},"chapter":{"id":51,"bookId":2,"arabic":"كتاب صفات المنافقين وأحكامهم","english":"Characteristics of The Hypocrites And Rulings Concerning Them","startHadith":6850,"endHadith":6870,"totalHadiths":21},"version":{"name":"muslim","title":"Sahih Muslim","chapters":57}}