{"id":203,"idInBook":2846,"chapterId":11,"bookId":14,"arabic":"وَعَنِ ابْنِ عَبَّاسٍ عَنِ النَّبِيِّ صَلَّى اللَّهُ عَلَيْهِ وَسَلَّمَ قَالَ: «الشَّرِيكُ شَفِيعٌ وَالشُّفْعَةُ فِي كل شَيْء» . رَوَاهُ التِّرْمِذِيّ قَالَ:\nوَقَدْ رُوِيَ عَنِ ابْنِ أَبِي مُلَيْكَةَ عَنِ النَّبِيِّ صَلَّى اللَّهُ عَلَيْهِ وَسَلَّمَ مُرْسَلًا وَهُوَ أصح","english":{"narrator":"","text":"Ibn ‘Abbas reported the Prophet as saying, \"The partner has first right to buy neighbouring property and the option to buy applies to everything.” \n\nTirmidhi transmitted it, saying it has been transmitted on the authority of Ibn Abu Mulaika who quoted the Prophet in mursal form, and it is sounder."},"hadithNumber":2846,"hadithId":203,"reference":"11:203","meta":{"id":"mishkat_almasabih","length":4428,"totalChapters":25,"arabic":{"title":"مشكاة المصابيح","author":"الإمام الكاتب التبريزي"},"english":{"title":"Mishkat Al Masabih","author":"Al-Khatib Al-Tabrizi"}},"chapter":{"id":11,"bookId":14,"arabic":"كتاب البيوع","english":"Business Transactions","startHadith":2644,"endHadith":2917,"totalHadiths":274},"version":{"name":"mishkat_almasabih","title":"Mishkat Al Masabih","chapters":25}}