{"id":19,"idInBook":3266,"chapterId":14,"bookId":14,"arabic":"وَعَنْ أُمِّ سَلَمَةَ قَالَتْ: قَالَ رَسُولُ اللَّهِ صَلَّى اللَّهُ عَلَيْهِ وَسَلَّمَ: «إِذَا كَانَ عِنْدَ مكَاتب إحداكن وَفَاء فلنحتجب مِنْهُ» . رَوَاهُ التِّرْمِذِيُّ وَأَبُو دَاوُدَ وَابْنُ مَاجَهْ","english":{"narrator":"","text":"Umm Salama reported God's Messenger as spying, “When a slave of one of you women has made an agreement to purchase his freedom and can pay the full price, she must veil herself from him.” \n\nTirmidhi, Abu Dawud and Ibn Majah transmitted it."},"hadithNumber":3266,"hadithId":19,"reference":"14:19","meta":{"id":"mishkat_almasabih","length":4428,"totalChapters":25,"arabic":{"title":"مشكاة المصابيح","author":"الإمام الكاتب التبريزي"},"english":{"title":"Mishkat Al Masabih","author":"Al-Khatib Al-Tabrizi"}},"chapter":{"id":14,"bookId":14,"arabic":"كتاب العتق","english":"Emancipation","startHadith":3248,"endHadith":3271,"totalHadiths":24},"version":{"name":"mishkat_almasabih","title":"Mishkat Al Masabih","chapters":25}}