{"id":3,"idInBook":3,"chapterId":1,"bookId":14,"arabic":"وَعَنِ ابْنِ عُمَرَ قَالَ: قَالَ رَسُولُ اللَّهِ صَلَّى اللَّهُ عَلَيْهِ وَسَلَّمَ: \n\" بُنِيَ الْإِسْلَامُ عَلَى خَمْسٍ: شَهَادَةِ أَنْ لَا إِلَهَ إِلَّا اللَّهُ وَأَنَّ مُحَمَّدًا عَبْدُهُ وَرَسُولُهُ وَإِقَامِ الصَّلَاةِ وَإِيتَاءِ الزَّكَاةِ وَالْحَجِّ وَصَوْمِ رَمَضَانَ \"","english":{"narrator":"Ibn ‘Umar reported God's messenger as saying, “Islam is based on five things:","text":"the testimony that there is no god but God and that Muhammad is His servant and messenger, the observance of the prayer, the payment of zakat, the Pilgrimage, and the fast during Ramadan.”\n\n(Bukhari and Muslim.)"},"hadithNumber":3,"hadithId":3,"reference":"1:3","meta":{"id":"mishkat_almasabih","length":4428,"totalChapters":25,"arabic":{"title":"مشكاة المصابيح","author":"الإمام الكاتب التبريزي"},"english":{"title":"Mishkat Al Masabih","author":"Al-Khatib Al-Tabrizi"}},"chapter":{"id":1,"bookId":14,"arabic":"كتاب الإيمان","english":"Faith","startHadith":1,"endHadith":188,"totalHadiths":188},"version":{"name":"mishkat_almasabih","title":"Mishkat Al Masabih","chapters":25}}