{"id":89,"idInBook":3987,"chapterId":20,"bookId":14,"arabic":"وَعَنْ مُحَمَّدِ بْنِ عَلِيِّ بْنِ حُسَيْنٍ عَنْ عَليّ بن أبي طَالب قَالَ: عَقَّ رَسُولُ اللَّهِ صَلَّى اللَّهُ عَلَيْهِ وَسَلَّمَ عَنِ الْحَسَنِ بِشَاةٍ وَقَالَ: «يَا فَاطِمَةُ احْلِقِي رَأْسَهُ وَتَصَدَّقِي بِزِنَةِ شَعْرِهِ فِضَّةً» فَوَزَنَّاهُ فَكَانَ وَزْنُهُ دِرْهَمًا أَوْ بَعْضَ دِرْهَمٍ. رَوَاهُ التِّرْمِذِيُّ وَقَالَ: هَذَا حَدِيثٌ حَسَنٌ غَرِيبٌ وَإِسْنَادُهُ لَيْسَ بِمُتَّصِلٍ لِأَنَّ مُحَمَّدَ بْنَ عَلِيِّ بْنِ حُسَيْنٍ لَمْ يُدْرِكْ عَلِيَّ بْنَ أَبِي طَالِبٍ","english":{"narrator":"","text":"Muhammad b. ‘All b. Husain quoted ‘Ali b. Abu Talib as saying that God’s messenger sacrificed a sheep on the seventh day for al-Hasan and said, “Shave his head, Fatima, and give the weight of his hair in silver as sadaqa.” So they weighed it and it amounted to a dirham or part of a dirham. \n\nTirmidhi transmitted it, saying this is a hasan gharib tradition, but its isnad is not fully connected because Muhammad b. ‘Ali b. Husain was not born in the time of ‘Ali b. Abu Talib."},"hadithNumber":3987,"hadithId":89,"reference":"20:89","meta":{"id":"mishkat_almasabih","length":4428,"totalChapters":25,"arabic":{"title":"مشكاة المصابيح","author":"الإمام الكاتب التبريزي"},"english":{"title":"Mishkat Al Masabih","author":"Al-Khatib Al-Tabrizi"}},"chapter":{"id":20,"bookId":14,"arabic":"كتاب الصيد والذبائح","english":"Game and Animals Which May Be Slaughtered","startHadith":3899,"endHadith":3991,"totalHadiths":93},"version":{"name":"mishkat_almasabih","title":"Mishkat Al Masabih","chapters":25}}