{"id":207,"idInBook":1649,"chapterId":5,"bookId":14,"arabic":"وَعَنِ ابْنِ عَبَّاسٍ قَالَ: قَالَ رَسُولُ اللَّهِ صَلَّى اللَّهُ عَلَيْهِ وَسَلَّمَ:\nمَنْ كَانَ لَهُ فرطان من متي أَدْخَلَهُ اللَّهُ بِهِمَا الْجَنَّةَ \". فَقَالَتْ عَائِشَةُ: فَمَنْ كَانَ لَهُ فَرَطٌ مَنْ أُمَّتِكَ؟ قَالَ: «وَمَنْ كَانَ لَهُ فَرَطٌ يَا مُوَفَّقَةُ» . فَقَالَتْ: فَمَنْ لَمْ يَكُنْ لَهُ فَرَطٌ مِنْ أُمَّتِكَ؟ قَالَ: «فَأَنَا فَرَطُ أُمَّتِي لَنْ يُصَابُوا بِمِثْلِي» . رَوَاهُ التِّرْمِذِيُّ وَقَالَ: هَذَا حَدِيثٌ غَرِيبٌ","english":{"narrator":"","text":"Ibn ‘Abbas reported God’s messenger as saying, “If any member of my people has two children who die before him, God will cause him to enter paradise on their account.” ‘A’isha asked, “Does it apply to a member of your people who has one child who dies before him?” He replied, “It does, you who have been helped by God to ask this.” She then asked, “What about a member of your people who has no children who die before him?” He replied, “I am the one who dies before my people, and they will never suffer any loss to compare with the loss of me.” \n\nTirmidhi transmitted it, saying this is a gharib tradition."},"hadithNumber":1649,"hadithId":207,"reference":"5:207","meta":{"id":"mishkat_almasabih","length":4428,"totalChapters":25,"arabic":{"title":"مشكاة المصابيح","author":"الإمام الكاتب التبريزي"},"english":{"title":"Mishkat Al Masabih","author":"Al-Khatib Al-Tabrizi"}},"chapter":{"id":5,"bookId":14,"arabic":"كتاب الجنائز","english":"Funerals","startHadith":1443,"endHadith":1685,"totalHadiths":243},"version":{"name":"mishkat_almasabih","title":"Mishkat Al Masabih","chapters":25}}