{"id":65,"idInBook":2549,"chapterId":37,"bookId":5,"arabic":"حَدَّثَنَا قُتَيْبَةُ، حَدَّثَنَا أَبُو عَوَانَةَ، عَنْ قَتَادَةَ، عَنْ أَبِي بُرْدَةَ بْنِ أَبِي مُوسَى، عَنْ أَبِيهِ، قَالَ يَا بُنَىَّ لَوْ رَأَيْتَنَا وَنَحْنُ مَعَ رَسُولِ اللَّهِ صلى الله عليه وسلم وَأَصَابَتْنَا السَّمَاءُ لَحَسِبْتَ أَنَّ رِيحَنَا رِيحُ الضَّأْنِ ‏.‏ قَالَ أَبُو عِيسَى هَذَا حَدِيثٌ صَحِيحٌ ‏.‏ وَمَعْنَى هَذَا الْحَدِيثِ أَنَّهُ كَانَ ثِيَابَهُمُ الصُّوفُ فَكَانَ إِذَا أَصَابَهُمُ الْمَطَرُ يَجِيءُ مِنْ ثِيَابِهِمْ رِيحُ الضَّأْنِ ‏.‏","english":{"narrator":"Abu Burdah bin Abi Musa narrated that his father said:","text":"\"O my son! If you saw us when we were with the Prophet(s.a.w) and the sky poured upon us, you would think that our smell was the smell of sheep.\"  The meaning of this Hadith\nis that their garments were of wool,\nso when the rain fell upon them,\nthe smell coming from their clothes\nwas that of sheep."},"hadithNumber":2549,"hadithId":65,"reference":"37:65","meta":{"id":"tirmidhi","length":3956,"totalChapters":49,"arabic":{"title":"جامع الترمذي","author":"الإمام أبو عيسى محمد بن عيسى الترمذي"},"english":{"title":"Jami At Tirmidhi","author":"Imam Abu Isa Muhammad ibn Isa al-Tirmidhi"}},"chapter":{"id":37,"bookId":5,"arabic":"كتاب صفة القيامة والرقائق والورع عن رسول الله صلى الله","english":"Chapters on the description of the Day of Judgement, Ar-Riqaq, and Al-Wara'","startHadith":2485,"endHadith":2592,"totalHadiths":108},"version":{"name":"tirmidhi","title":"Jami At Tirmidhi","chapters":49}}