{"id":248,"idInBook":3945,"chapterId":49,"bookId":5,"arabic":"حَدَّثَنَا مَحْمُودُ بْنُ غَيْلاَنَ، قَالَ حَدَّثَنَا عَبْدُ الرَّزَّاقِ، قَالَ أَخْبَرَنَا ابْنُ جُرَيْجٍ، قَالَ أَخْبَرَنِي أَبُو الزُّبَيْرِ، أَنَّهُ سَمِعَ جَابِرَ بْنَ عَبْدِ اللَّهِ، يَقُولُ سَمِعْتُ رَسُولَ اللَّهِ صلى الله عليه وسلم يَقُولُ وَجَنَازَةُ سَعْدِ بْنِ مُعَاذٍ بَيْنَ أَيْدِيهِمْ ‏\n\"‏ اهْتَزَّ لَهُ عَرْشُ الرَّحْمَنِ ‏\"‏ ‏. وَفِي الْبَابِ عَنْ أُسَيْدِ بْنِ حُضَيْرٍ وَأَبِي سَعِيدٍ وَرُمَيْثَةَ ‏.‏هَذَا حَدِيثٌ حَسَنٌ صَحِيحٌ ‏.‏","english":{"narrator":"Narrated Jabir bin 'Abdullah:","text":"\"I heard the Messenger of Allah (ﷺ), saying while the funeral of Sa'd bin Mu'adh was in front of them: 'The Throne of Ar-Rahman shook due to it.'\""},"hadithNumber":3945,"hadithId":248,"reference":"49:248","meta":{"id":"tirmidhi","length":3956,"totalChapters":49,"arabic":{"title":"جامع الترمذي","author":"الإمام أبو عيسى محمد بن عيسى الترمذي"},"english":{"title":"Jami At Tirmidhi","author":"Imam Abu Isa Muhammad ibn Isa al-Tirmidhi"}},"chapter":{"id":49,"bookId":5,"arabic":"كتاب المناقب عن رسول الله صلى الله عليه وسلم","english":"Chapters on Virtues","startHadith":3698,"endHadith":4053,"totalHadiths":356},"version":{"name":"tirmidhi","title":"Jami At Tirmidhi","chapters":49}}