{"id":33,"idInBook":1657,"chapterId":15,"bookId":9,"arabic":"أَخْبَرَنَا سُلَيْمَانُ بْنُ حَرْبٍ  ، حَدَّثَنَا شُعْبَةُ  ، عَنْ أَيُّوبَ  ، عَنْ الْقَاسِمِ بْنِ رَبِيعَةَ  ، عَنْ عَبْدِ اللَّهِ بْنِ عَمْرٍو  ، قَالَ : قَالَ رَسُولُ اللَّهِ صَلَّى اللَّهُ عَلَيْهِ وَسَلَّمَ :\" دِيَةُ قَتِيلِ الْخَطَإِ شِبْهِ الْعَمْدِ، وَمَا كَانَ بِالسَّوْطِ وَالْعَصَا مِائَةٌ مِنْهَا : أَرْبَعُونَ فِي بُطُونِهَا أَوْلَادُهَا \"","english":{"narrator":"","text":""},"hadithNumber":1657,"hadithId":33,"reference":"15:33","meta":{"id":"darimi","length":3406,"totalChapters":23,"arabic":{"title":"سنن الدارمي","author":"الإمام أبو محمد عبد الرحمن بن عبد الله بن الدارمي"},"english":{"title":"Sunan Al Darimi","author":"Imam Abu Muhammad Abd al-Rahman ibn Abd Allah ibn al-Darimi"}},"chapter":{"id":15,"bookId":9,"arabic":"وَمِنْ كِتَابِ الدِّيَاتِ","english":"","startHadith":1625,"endHadith":1662,"totalHadiths":38},"version":{"name":"darimi","title":"Sunan Al Darimi","chapters":23}}