{"id":10,"idInBook":10,"chapterId":1,"bookId":9,"arabic":"أَخْبَرَنَا عُبَيْدُ اللَّهِ بْنُ مُوسَى  ، عَنْ سُفْيَانَ  ، عَنْ عَلْقَمَةَ بْنِ مَرْثَدٍ  ، عَنْ ابْنِ بُرَيْدَةَ  ، عَنْ أَبِيهِ  ، قَالَ : كَانَ رَسُولُ اللَّهِ صَلَّى اللَّهُ عَلَيْهِ وَسَلَّمَ\" يَتَوَضَّأُ لِكُلِّ صَلَاةٍ، حَتَّى كَانَ يَوْمُ فَتْحِ مَكَّةَ ، صَلَّى الصَّلَوَاتِ بِوُضُوءٍ وَاحِدٍ، وَمَسَحَ عَلَى خُفَّيْهِ \"، فَقَالَ لَهُ عُمَرُ : رَأَيْتُكَ صَنَعْتَ شَيْئًا لَمْ تَكُنْ تَصْنَعُهُ؟، قَالَ : \" إِنِّي عَمْدًا صَنَعْتُ يَا عُمَرُ \"، قَالَ أَبُو مُحَمَّد : فَدَلَّ فِعْلُ رَسُولِ اللَّهِ صَلَّى اللَّهُ عَلَيْهِ وَسَلَّمَ أَنَّ مَعْنَى قَوْلِ اللَّهِ تَعَالَى : # إِذَا قُمْتُمْ إِلَى الصَّلاةِ فَاغْسِلُوا وُجُوهَكُمْ سورة المائدة آية 6 #، لِكُلِّ مُحْدِثٍ، لَيْسَ لِلطَّاهِرِ، وَمِنْهُ قَوْلُ النَّبِيِّ صَلَّى اللَّهُ عَلَيْهِ وَسَلَّمَ : \" لَا وُضُوءَ إِلَّا مِنْ حَدَثٍ \"، وَاللَّهُ أَعْلَمُ","english":{"narrator":"","text":""},"hadithNumber":10,"hadithId":10,"reference":"1:10","meta":{"id":"darimi","length":3406,"totalChapters":23,"arabic":{"title":"سنن الدارمي","author":"الإمام أبو محمد عبد الرحمن بن عبد الله بن الدارمي"},"english":{"title":"Sunan Al Darimi","author":"Imam Abu Muhammad Abd al-Rahman ibn Abd Allah ibn al-Darimi"}},"chapter":{"id":1,"bookId":9,"arabic":"كِتَاب الطَّهَارَةِ","english":"","startHadith":1,"endHadith":510,"totalHadiths":510},"version":{"name":"darimi","title":"Sunan Al Darimi","chapters":23}}