{"id":55,"idInBook":2165,"chapterId":21,"bookId":9,"arabic":"أَخْبَرَنَا مُسْلِمُ بْنُ إِبْرَاهِيمَ  ، حَدَّثَنَا وُهَيْبٌ  ، حَدَّثَنَا خَالِدٌ  ، عَنْ أَبِي نَضْرَةَ  ، عَنْ أَبِي سَعِيدٍ الْخُدْرِيِّ  .\nح وَعَنْ عِكْرِمَةَ  : أَنَّ أَبَا بَكْرٍ الصِّدِّيقَ  \" جَعَلَ الْجَدَّ أَبًا \".\nحَدَّثَنَا مُحَمَّدُ بْنُ يُوسُفَ  ، حَدَّثَنَا سُفْيَانُ  ، عَنْ سُلَيْمَانَ الشَّيْبَانِيِّ  ، عَنْ كُرْدُوسٍ  ، عَن أبِى بُرْدَةَ  ، عَنْ أَبِي مُوسَى  : أنَّ أَبَا بَكْرٍ الصِّدِّيقِ   جَعَلَ الْجَدَّ أَبًا","english":{"narrator":"","text":""},"hadithNumber":2165,"hadithId":55,"reference":"21:55","meta":{"id":"darimi","length":3406,"totalChapters":23,"arabic":{"title":"سنن الدارمي","author":"الإمام أبو محمد عبد الرحمن بن عبد الله بن الدارمي"},"english":{"title":"Sunan Al Darimi","author":"Imam Abu Muhammad Abd al-Rahman ibn Abd Allah ibn al-Darimi"}},"chapter":{"id":21,"bookId":9,"arabic":"مِنْ كِتَابِ الْفَرَائِضِ","english":"","startHadith":2111,"endHadith":2435,"totalHadiths":325},"version":{"name":"darimi","title":"Sunan Al Darimi","chapters":23}}