{"id":130,"idInBook":2691,"chapterId":23,"bookId":9,"arabic":"حَدَّثَنَا عَبْدُ اللَّهِ بْنُ مَسْلَمَةَ  ، حَدَّثَنَا مُحَمَّدُ بْنُ عَبْدِ اللَّهِ بْنِ مُسْلِمٍ  ، عَنْ مُحَمَّدِ بْنِ شِهَابٍ  ، عَنْ حُمَيْدِ بْنِ عَبْدِ الرَّحْمَنِ  ، عَنْ أُمِّهِ   : أَنَّ رَسُولَ اللَّهِ صَلَّى اللَّهُ عَلَيْهِ وَسَلَّمَ سُئِلَ عَنْ قُلْ هُوَ اللَّهُ أَحَدٌ ، فَقَالَ :\" ثُلُثُ الْقُرْآنِ، أَوْ تَعْدِلُهُ \"","english":{"narrator":"","text":""},"hadithNumber":2691,"hadithId":130,"reference":"23:130","meta":{"id":"darimi","length":3406,"totalChapters":23,"arabic":{"title":"سنن الدارمي","author":"الإمام أبو محمد عبد الرحمن بن عبد الله بن الدارمي"},"english":{"title":"Sunan Al Darimi","author":"Imam Abu Muhammad Abd al-Rahman ibn Abd Allah ibn al-Darimi"}},"chapter":{"id":23,"bookId":9,"arabic":"وَمِنْ كِتَابِ فَضَائِلِ الْقُرْآنِ","english":"","startHadith":2562,"endHadith":2757,"totalHadiths":196},"version":{"name":"darimi","title":"Sunan Al Darimi","chapters":23}}