{"id":158,"idInBook":668,"chapterId":2,"bookId":9,"arabic":"أَخْبَرَنَا يَزِيدُ بْنُ هَارُونَ  ، أَنْبأَنَا عَاصِمٌ  ، عَنْ أَبِي الْوَلِيدِ هُوَ عَبْدُ اللَّهِ بْنُ الْحَارِثِ  ، عَنْ عَائِشَةَ  ، قَالَتْ : مَا كَانَ النَّبِيُّ صَلَّى اللَّهُ عَلَيْهِ وَسَلَّمَ يَجْلِسُ بَعْدَ الصَّلَاةِ إِلَّا قَدْرَ مَا يَقُولُ :\" اللَّهُمَّ أَنْتَ السَّلَامُ، وَمِنْكَ السَّلَامُ، تَبَارَكْتَ يَا ذَا الْجَلَالِ وَالْإِكْرَامِ \"","english":{"narrator":"","text":""},"hadithNumber":668,"hadithId":158,"reference":"2:158","meta":{"id":"darimi","length":3406,"totalChapters":23,"arabic":{"title":"سنن الدارمي","author":"الإمام أبو محمد عبد الرحمن بن عبد الله بن الدارمي"},"english":{"title":"Sunan Al Darimi","author":"Imam Abu Muhammad Abd al-Rahman ibn Abd Allah ibn al-Darimi"}},"chapter":{"id":2,"bookId":9,"arabic":"كِتَاب الصَّلَاةِ","english":"","startHadith":511,"endHadith":929,"totalHadiths":419},"version":{"name":"darimi","title":"Sunan Al Darimi","chapters":23}}