{"id":91,"idInBook":4806,"chapterId":45,"bookId":3,"arabic":"أَخْبَرَنَا إِسْمَاعِيلُ بْنُ مَسْعُودٍ، قَالَ حَدَّثَنَا بِشْرُ بْنُ الْمُفَضَّلِ، عَنْ خَالِدٍ الْحَذَّاءِ، عَنِ الْقَاسِمِ بْنِ رَبِيعَةَ، عَنْ يَعْقُوبَ بْنِ أَوْسٍ، عَنْ رَجُلٍ، مِنْ أَصْحَابِ النَّبِيِّ صلى الله عليه وسلم أَنَّ رَسُولَ اللَّهِ صلى الله عليه وسلم لَمَّا دَخَلَ مَكَّةَ يَوْمَ الْفَتْحِ قَالَ ‏\n\"‏ أَلاَ وَإِنَّ كُلَّ قَتِيلِ خَطَإِ الْعَمْدِ أَوْ شِبْهِ الْعَمْدِ قَتِيلِ السَّوْطِ وَالْعَصَا مِنْهَا أَرْبَعُونَ فِي بُطُونِهَا أَوْلاَدُهَا ‏\"‏ ‏.‏","english":{"narrator":"It was narrated from Ya'qub bin Aws, from a man among the Companions of the Prophet that:","text":"when the Messenger of Allah entered Makkah on the Day of the Conquest, he said: \"Indeed, every accidental killing on purpose, or resembling on purpose - killing with a whip or stick, for it are forty (she-camels) which their young in their wombs.\""},"hadithNumber":4806,"hadithId":91,"reference":"45:91","meta":{"id":"nasai","length":5758,"totalChapters":52,"arabic":{"title":"سنن النسائي","author":"الإمام أبو عبد الرحمن أحمد بن شعيب النسائي"},"english":{"title":"Sunan An Nasai","author":"Imam Ahmad ibn Shu'ayb al-Nasa'i"}},"chapter":{"id":45,"bookId":3,"arabic":"كتاب القسامة","english":"The Book of Oaths (qasamah), Retaliation and Blood Money","startHadith":4716,"endHadith":4879,"totalHadiths":164},"version":{"name":"nasai","title":"Sunan An Nasai","chapters":52}}