{"id":42,"idInBook":5429,"chapterId":49,"bookId":3,"arabic":"أَخْبَرَنَا إِسْحَاقُ بْنُ إِبْرَاهِيمَ، قَالَ أَنْبَأَنَا وَكِيعٌ، قَالَ حَدَّثَنَا هِشَامُ بْنُ عُرْوَةَ، عَنْ أَبِيهِ، عَنْ عَائِشَةَ، قَالَتْ جَاءَتْ هِنْدٌ إِلَى رَسُولِ اللَّهِ صلى الله عليه وسلم فَقَالَتْ يَا رَسُولَ اللَّهِ إِنَّ أَبَا سُفْيَانَ رَجُلٌ شَحِيحٌ وَلاَ يُنْفِقُ عَلَىَّ وَوَلَدِي مَا يَكْفِينِي أَفَآخُذُ مِنْ مَالِهِ وَلاَ يَشْعُرُ قَالَ ‏\n\"‏ خُذِي مَا يَكْفِيكِ وَوَلَدَكِ بِالْمَعْرُوفِ ‏\"‏ ‏.‏","english":{"narrator":"It was narrated that 'Aishah said:","text":"\"Hind came to the Messenger of Allah  and said : 'O Messenger of Allah, Abu Sufyan is a stingy man who does not spend enough on my child and I. Can I take from his wealth without him realizing?' He said: 'Take what is sufficient for you and your child on a reasonable basis.'\""},"hadithNumber":5429,"hadithId":42,"reference":"49:42","meta":{"id":"nasai","length":5758,"totalChapters":52,"arabic":{"title":"سنن النسائي","author":"الإمام أبو عبد الرحمن أحمد بن شعيب النسائي"},"english":{"title":"Sunan An Nasai","author":"Imam Ahmad ibn Shu'ayb al-Nasa'i"}},"chapter":{"id":49,"bookId":3,"arabic":"كتاب آداب القضاة","english":"The Book of the Etiquette of Judges","startHadith":5388,"endHadith":5436,"totalHadiths":49},"version":{"name":"nasai","title":"Sunan An Nasai","chapters":52}}