{"id":6,"idInBook":437,"chapterId":10,"bookId":7,"arabic":"حَدَّثَنِي يَحْيَى، عَنْ مَالِكٍ، عَنْ هِشَامِ بْنِ عُرْوَةَ، عَنْ أَبِيهِ، أَنَّهُ كَانَ يَأْكُلُ يَوْمَ عِيدِ الْفِطْرِ قَبْلَ أَنْ يَغْدُوَ ‏.‏","english":{"narrator":"","text":"Yahya related to me from Malik from Hisham ibn Urwa from his\nfather that he used to eat on the day of the id al-Fitr before going\nout."},"hadithNumber":437,"hadithId":6,"reference":"10:6","meta":{"id":"malik","length":1858,"totalChapters":61,"arabic":{"title":"موطأ مالك","author":"الإمام مالك بن أنس"},"english":{"title":"Muwatta Malik","author":"Imam Malik ibn Anas"}},"chapter":{"id":10,"bookId":7,"arabic":"كتاب العيدين","english":"The Two 'Ids","startHadith":432,"endHadith":445,"totalHadiths":14},"version":{"name":"malik","title":"Muwatta Malik","chapters":61}}