{"id":35,"idInBook":2512,"chapterId":15,"bookId":4,"arabic":"حَدَّثَنَا عَبْدُ اللَّهِ بْنُ الْجَرَّاحِ، عَنْ عَبْدِ اللَّهِ بْنِ يَزِيدَ، عَنْ مُوسَى بْنِ عُلَىِّ بْنِ رَبَاحٍ، عَنْ أَبِيهِ، عَنْ عَبْدِ الْعَزِيزِ بْنِ مَرْوَانَ، قَالَ سَمِعْتُ أَبَا هُرَيْرَةَ، يَقُولُ سَمِعْتُ رَسُولَ اللَّهِ صلى الله عليه وسلم يَقُولُ ‏:‏ ‏\n\"‏ شَرُّ مَا فِي رَجُلٍ شُحٌّ هَالِعٌ وَجُبْنٌ خَالِعٌ ‏\"‏ ‏.‏","english":{"narrator":"Narrated AbuHurayrah:","text":"I heard the Messenger of Allah (ﷺ) say: What is evil in a man are alarming niggardliness and unrestrained cowardice."},"hadithNumber":2512,"hadithId":35,"reference":"15:35","meta":{"id":"abudawud","length":5274,"totalChapters":43,"arabic":{"title":"سنن أبي داود","author":"الإمام سليمان بن الأشعث أبو داود السجستاني"},"english":{"title":"Sunan Abi Dawud","author":"Imam Sulayman ibn al-Ash'ath Abu Dawud al-Sijistani"}},"chapter":{"id":15,"bookId":4,"arabic":"كتاب الجهاد","english":"Jihad (Kitab Al-Jihad)","startHadith":2478,"endHadith":2788,"totalHadiths":311},"version":{"name":"abudawud","title":"Sunan Abi Dawud","chapters":43}}