{"id":154,"idInBook":154,"chapterId":1,"bookId":4,"arabic":"حَدَّثَنَا عَلِيُّ بْنُ الْحُسَيْنِ الدِّرْهَمِيُّ، حَدَّثَنَا ابْنُ دَاوُدَ، عَنْ بُكَيْرِ بْنِ عَامِرٍ، عَنْ أَبِي زُرْعَةَ بْنِ عَمْرِو بْنِ جَرِيرٍ، أَنَّ جَرِيرًا، بَالَ ثُمَّ تَوَضَّأَ فَمَسَحَ عَلَى الْخُفَّيْنِ وَقَالَ مَا يَمْنَعُنِي أَنْ أَمْسَحَ وَقَدْ رَأَيْتُ رَسُولَ اللَّهِ صلى الله عليه وسلم يَمْسَحُ قَالُوا إِنَّمَا كَانَ ذَلِكَ قَبْلَ نُزُولِ الْمَائِدَةِ ‏.‏ قَالَ مَا أَسْلَمْتُ إِلاَّ بَعْدَ نُزُولِ الْمَائِدَةِ ‏.‏","english":{"narrator":"Abu Zur’ah b. ‘Amr b. Jarir said :","text":"Jarir urinated. He then performed ablution and wiped over the socks. He said: What can prevent me from wiping (over the socks); I saw the Messenger of Allah (doing so). They (the people) said: This (action of yours) might be valid before the revelation of Surat al-Ma’idah. He replied: I embraced Islam after the revelation of Surat al-Ma’idah."},"hadithNumber":154,"hadithId":154,"reference":"1:154","meta":{"id":"abudawud","length":5274,"totalChapters":43,"arabic":{"title":"سنن أبي داود","author":"الإمام سليمان بن الأشعث أبو داود السجستاني"},"english":{"title":"Sunan Abi Dawud","author":"Imam Sulayman ibn al-Ash'ath Abu Dawud al-Sijistani"}},"chapter":{"id":1,"bookId":4,"arabic":"كتاب الطهارة","english":"Purification (Kitab Al-Taharah)","startHadith":1,"endHadith":390,"totalHadiths":390},"version":{"name":"abudawud","title":"Sunan Abi Dawud","chapters":43}}