{"id":29,"idInBook":3445,"chapterId":24,"bookId":4,"arabic":"حَدَّثَنَا مُوسَى بْنُ إِسْمَاعِيلَ، حَدَّثَنَا حَمَّادٌ، عَنْ أَيُّوبَ، وَهِشَامٍ، وَحَبِيبٍ، عَنْ مُحَمَّدِ بْنِ سِيرِينَ، عَنْ أَبِي هُرَيْرَةَ، أَنَّ النَّبِيَّ صلى الله عليه وسلم قَالَ ‏\n\"‏ مَنِ اشْتَرَى شَاةً مُصَرَّاةً فَهُوَ بِالْخِيَارِ ثَلاَثَةَ أَيَّامٍ إِنْ شَاءَ رَدَّهَا وَصَاعًا مِنْ طَعَامٍ لاَ سَمْرَاءَ ‏\"‏ ‏.‏","english":{"narrator":"Narrated Abu Hurairah:","text":"The Prophet (ﷺ) as saying: If anyone buys sheep whose udders have been tied up, he has option for three days: he may return it if he desires with a sa' of any grain, not (necessarily) wheat."},"hadithNumber":3445,"hadithId":29,"reference":"24:29","meta":{"id":"abudawud","length":5274,"totalChapters":43,"arabic":{"title":"سنن أبي داود","author":"الإمام سليمان بن الأشعث أبو داود السجستاني"},"english":{"title":"Sunan Abi Dawud","author":"Imam Sulayman ibn al-Ash'ath Abu Dawud al-Sijistani"}},"chapter":{"id":24,"bookId":4,"arabic":"كتاب الإجارة","english":"Wages (Kitab Al-Ijarah)","startHadith":3417,"endHadith":3571,"totalHadiths":155},"version":{"name":"abudawud","title":"Sunan Abi Dawud","chapters":43}}