{"id":40,"idInBook":2081,"chapterId":13,"bookId":6,"arabic":"حَدَّثَنَا أَبُو بَكْرِ بْنُ أَبِي شَيْبَةَ، حَدَّثَنَا يَحْيَى بْنُ يَمَانٍ، عَنْ مَعْمَرٍ، عَنِ الزُّهْرِيِّ، عَنْ عُرْوَةَ، عَنْ عَائِشَةَ، أَنَّ النَّبِيَّ صلى الله عليه وسلم كَانَ إِذَا سَافَرَ أَقْرَعَ بَيْنَ نِسَائِهِ ‏.‏","english":{"narrator":"It was narrated from 'Aishah that :","text":"when the Prophet (ﷺ) traveled, he would cast lots among his wives (to decide which one would accompany him)."},"hadithNumber":2081,"hadithId":40,"reference":"13:40","meta":{"id":"ibnmajah","length":4341,"totalChapters":38,"arabic":{"title":"سنن ابن ماجه","author":"الإمام محمد بن يزيد بن ماجه القزويني"},"english":{"title":"Sunan Ibn Majah","author":"Imam Muhammad ibn Yazid Ibn Majah al-Qazwini"}},"chapter":{"id":13,"bookId":6,"arabic":"كتاب الأحكام","english":"The Chapters on Rulings","startHadith":2042,"endHadith":2108,"totalHadiths":67},"version":{"name":"ibnmajah","title":"Sunan Ibn Majah","chapters":38}}