{"id":88,"idInBook":624,"chapterId":5,"bookId":6,"arabic":"حَدَّثَنَا أَبُو بَكْرِ بْنُ خَلاَّدٍ الْبَاهِلِيُّ، حَدَّثَنَا وَكِيعٌ، عَنِ ابْنِ أَبِي ذِئْبٍ، عَنْ إِسْحَاقَ بْنِ يَزِيدَ الْهُذَلِيِّ، عَنْ عَوْنِ بْنِ عَبْدِ اللَّهِ بْنِ عُتْبَةَ، عَنِ ابْنِ مَسْعُودٍ، قَالَ قَالَ رَسُولُ اللَّهِ ـ صلى الله عليه وسلم ـ ‏\n\"‏ إِذَا رَكَعَ أَحَدُكُمْ فَلْيَقُلْ فِي رُكُوعِهِ سُبْحَانَ رَبِّيَ الْعَظِيمِ ‏.‏ ثَلاَثًا فَإِذَا فَعَلَ ذَلِكَ فَقَدْ تَمَّ رُكُوعُهُ وَإِذَا سَجَدَ أَحَدُكُمْ فَلْيَقُلْ فِي سُجُودِهِ سُبْحَانَ رَبِّيَ الأَعْلَى ثَلاَثًا. فَإِذَا فَعَلَ ذَلِكَ فَقَدْ تَمَّ سُجُودُهُ، وَذَلِكَ أَدْنَاهُ ‏\"‏ ‏.‏","english":{"narrator":"It was\nnarrated that Ibn Mas’ud said:","text":"“The Messenger of Allah (ﷺ)\nsaid: ‘When anyone of you bows, let him say in his bowing: “Subhana\nRabbiyal-‘Azim (Glory is to my Lord, the Most Great)” three\ntimes; if\nhe does that his bowing will be complete. And when anyone\nof you\nprostrates, let him say in his prostration, ‘Subhana\nRabbiyal-A’la\n(Glory if to my Lord, the Most High)” three times;\nif he does that,\nhis prostration will be complete, and that is the\nminimum.’”"},"hadithNumber":624,"hadithId":88,"reference":"5:88","meta":{"id":"ibnmajah","length":4341,"totalChapters":38,"arabic":{"title":"سنن ابن ماجه","author":"الإمام محمد بن يزيد بن ماجه القزويني"},"english":{"title":"Sunan Ibn Majah","author":"Imam Muhammad ibn Yazid Ibn Majah al-Qazwini"}},"chapter":{"id":5,"bookId":6,"arabic":"كتاب إقامة الصلاة والسنة فيها","english":"Establishing the Prayer and the Sunnah Regarding Them","startHadith":537,"endHadith":1166,"totalHadiths":630},"version":{"name":"ibnmajah","title":"Sunan Ibn Majah","chapters":38}}