{"id":219,"idInBook":1679,"chapterId":25,"bookId":1,"arabic":"حَدَّثَنِي عَبْدُ اللَّهِ بْنُ مُحَمَّدٍ، حَدَّثَنَا أَبُو عَامِرٍ، حَدَّثَنَا قُرَّةُ، عَنْ مُحَمَّدِ بْنِ سِيرِينَ، قَالَ أَخْبَرَنِي عَبْدُ الرَّحْمَنِ بْنُ أَبِي بَكْرَةَ، عَنْ أَبِي بَكْرَةَ،، وَرَجُلٌ، أَفْضَلُ فِي نَفْسِي مِنْ عَبْدِ الرَّحْمَنِ حُمَيْدُ بْنُ عَبْدِ الرَّحْمَنِ عَنْ أَبِي بَكْرَةَ ـ رضى الله عنه ـ قَالَ خَطَبَنَا النَّبِيُّ صلى الله عليه وسلم يَوْمَ النَّحْرِ، قَالَ ‏\"‏ أَتَدْرُونَ أَىُّ يَوْمٍ هَذَا ‏\"‏‏.‏ قُلْنَا اللَّهُ وَرَسُولُهُ أَعْلَمُ‏.‏ فَسَكَتَ حَتَّى ظَنَنَّا أَنَّهُ سَيُسَمِّيهِ بِغَيْرِ اسْمِهِ‏.‏ قَالَ ‏\"‏ أَلَيْسَ يَوْمَ النَّحْرِ ‏\"‏‏.‏ قُلْنَا بَلَى‏.‏ قَالَ ‏\"‏ أَىُّ شَهْرٍ هَذَا ‏\"‏‏.‏ قُلْنَا اللَّهُ وَرَسُولُهُ أَعْلَمُ‏.‏ فَسَكَتَ حَتَّى ظَنَنَّا أَنَّهُ سَيُسَمِّيهِ بِغَيْرِ اسْمِهِ‏.‏ فَقَالَ ‏\"‏ أَلَيْسَ ذُو الْحَجَّةِ ‏\"‏‏.‏ قُلْنَا بَلَى‏.‏ قَالَ ‏\"‏ أَىُّ بَلَدٍ هَذَا ‏\"‏‏.‏ قُلْنَا اللَّهُ وَرَسُولُهُ أَعْلَمُ‏.‏ فَسَكَتَ حَتَّى ظَنَنَّا أَنَّهُ سَيُسَمِّيهِ بِغَيْرِ اسْمِهِ‏.‏ قَالَ ‏\"‏ أَلَيْسَتْ بِالْبَلْدَةِ الْحَرَامِ ‏\"‏‏.‏ قُلْنَا بَلَى‏.‏ قَالَ ‏\"‏ فَإِنَّ دِمَاءَكُمْ وَأَمْوَالَكُمْ عَلَيْكُمْ حَرَامٌ، كَحُرْمَةِ يَوْمِكُمْ هَذَا، فِي شَهْرِكُمْ هَذَا، فِي بَلَدِكُمْ هَذَا، إِلَى يَوْمِ تَلْقَوْنَ رَبَّكُمْ‏.‏ أَلاَ هَلْ بَلَّغْتُ ‏\"‏‏.‏ قَالُوا نَعَمْ‏.‏ قَالَ ‏\"‏ اللَّهُمَّ اشْهَدْ، فَلْيُبَلِّغِ الشَّاهِدُ الْغَائِبَ، فَرُبَّ مُبَلَّغٍ أَوْعَى مِنْ سَامِعٍ، فَلاَ تَرْجِعُوا بَعْدِي كُفَّارًا يَضْرِبُ بَعْضُكُمْ رِقَابَ بَعْضٍ ‏\"‏‏.‏","english":{"narrator":"Narrated Abu Bakra:","text":"The Prophet (ﷺ) delivered to us a sermon on the Day of Nahr. He said, \"Do you know what is the day \ntoday?\" We said, \"Allah and His Apostle know better.\" He remained silent till we thought that he \nmight give that day another name. He said, \"Isn't it the Day of Nahr?\" We said, \"It is.\" He further \nasked, \"Which month is this?\" We said, \"Allah and His Apostle know better.\" He remained silent till \nwe thought that he might give it another name. He then said, \"Isn't it the month of Dhul-Hijja?\" We \nreplied: \"Yes! It is.\" He further asked, \"What town is this?\" We replied, \"Allah and His Apostle know \nit better.\" He remained silent till we thought that he might give it another name. He then said, \"Isn't it \nthe forbidden (Sacred) town (of Mecca)?\" We said, \"Yes. It is.\" He said, \"No doubt, your blood and \nyour properties are sacred to one another like the sanctity of this day of yours, in this month of yours, \nin this town of yours, till the day you meet your Lord. No doubt! Haven't I conveyed Allah's message \nto you? They said, \"Yes.\" He said, \"O Allah! Be witness. So it is incumbent upon those who are \npresent to convey it (this information) to those who are absent because the informed one might \ncomprehend it (what I have said) better than the present audience, who will convey it to him. Beware! \nDo not renegade (as) disbelievers after me by striking the necks (cutting the throats) of one another.\""},"hadithNumber":1679,"vol":3,"hadithId":219,"reference":"25:219","meta":{"id":"bukhari","length":7563,"totalChapters":97,"arabic":{"title":"صحيح البخاري","author":"الإمام محمد بن إسماعيل البخاري"},"english":{"title":"Sahih Al Bukhari","author":"Imam Muhammad ibn Ismail al-Bukhari"}},"chapter":{"id":25,"bookId":1,"arabic":"كتاب الحج","english":"Hajj (Pilgrimage)","startHadith":1461,"endHadith":1707,"totalHadiths":247},"version":{"name":"bukhari","title":"Sahih Al Bukhari","chapters":97}}