{"id":111,"idInBook":1933,"chapterId":30,"bookId":1,"arabic":"حَدَّثَنَا عُبَيْدُ اللَّهِ بْنُ مُوسَى، عَنِ ابْنِ عُيَيْنَةَ، عَنْ عُبَيْدِ اللَّهِ بْنِ أَبِي يَزِيدَ، عَنِ ابْنِ عَبَّاسٍ ـ رضى الله عنهما ـ قَالَ مَا رَأَيْتُ النَّبِيَّ صلى الله عليه وسلم يَتَحَرَّى صِيَامَ يَوْمٍ فَضَّلَهُ عَلَى غَيْرِهِ، إِلاَّ هَذَا الْيَوْمَ يَوْمَ عَاشُورَاءَ وَهَذَا الشَّهْرَ‏.‏ يَعْنِي شَهْرَ رَمَضَانَ‏.‏","english":{"narrator":"Narrated Ibn `Abbas:","text":"I never saw the Prophet (ﷺ) seeking to fast on a day that he favored more than another except this day, the day of 'Ashura', and this month, meaning the month of Ramadan."},"hadithNumber":1933,"vol":3,"hadithId":111,"reference":"30:111","meta":{"id":"bukhari","length":7563,"totalChapters":97,"arabic":{"title":"صحيح البخاري","author":"الإمام محمد بن إسماعيل البخاري"},"english":{"title":"Sahih Al Bukhari","author":"Imam Muhammad ibn Ismail al-Bukhari"}},"chapter":{"id":30,"bookId":1,"arabic":"كتاب الصوم","english":"Fasting","startHadith":1823,"endHadith":1934,"totalHadiths":112},"version":{"name":"bukhari","title":"Sahih Al Bukhari","chapters":97}}