{"id":87,"idInBook":2059,"chapterId":34,"bookId":1,"arabic":"حَدَّثَنَا عَلِيُّ بْنُ عَبْدِ اللَّهِ، حَدَّثَنَا سُفْيَانُ، قَالَ الَّذِي حَفِظْنَاهُ مِنْ عَمْرِو بْنِ دِينَارٍ سَمِعَ طَاوُسًا، يَقُولُ سَمِعْتُ ابْنَ عَبَّاسٍ ـ رضى الله عنهما ـ يَقُولُ أَمَّا الَّذِي نَهَى عَنْهُ النَّبِيُّ صلى الله عليه وسلم فَهْوَ الطَّعَامُ أَنْ يُبَاعَ حَتَّى يُقْبَضَ‏.‏ قَالَ ابْنُ عَبَّاسٍ وَلاَ أَحْسِبُ كُلَّ شَىْءٍ إِلاَّ مِثْلَهُ‏.‏","english":{"narrator":"Narrated Ibn `Abbas:","text":"The Prophet (ﷺ) forbade the selling of foodstuff before receiving it. I consider that all types of sellings \nshould be done similarly."},"hadithNumber":2059,"vol":3,"hadithId":87,"reference":"34:87","meta":{"id":"bukhari","length":7563,"totalChapters":97,"arabic":{"title":"صحيح البخاري","author":"الإمام محمد بن إسماعيل البخاري"},"english":{"title":"Sahih Al Bukhari","author":"Imam Muhammad ibn Ismail al-Bukhari"}},"chapter":{"id":34,"bookId":1,"arabic":"كتاب البيوع","english":"Sales and Trade","startHadith":1973,"endHadith":2156,"totalHadiths":184},"version":{"name":"bukhari","title":"Sahih Al Bukhari","chapters":97}}