{"id":34,"idInBook":281,"chapterId":5,"bookId":1,"arabic":"حَدَّثَنَا عَبْدُ اللَّهِ بْنُ يُوسُفَ، قَالَ أَخْبَرَنَا مَالِكٌ، عَنْ هِشَامِ بْنِ عُرْوَةَ، عَنْ أَبِيهِ، عَنْ زَيْنَبَ بِنْتِ أَبِي سَلَمَةَ، عَنْ أُمِّ سَلَمَةَ أُمِّ الْمُؤْمِنِينَ، أَنَّهَا قَالَتْ جَاءَتْ أُمُّ سُلَيْمٍ امْرَأَةُ أَبِي طَلْحَةَ إِلَى رَسُولِ اللَّهِ صلى الله عليه وسلم فَقَالَتْ يَا رَسُولَ اللَّهِ، إِنَّ اللَّهَ لاَ يَسْتَحْيِي مِنَ الْحَقِّ، هَلْ عَلَى الْمَرْأَةِ مِنْ غُسْلٍ إِذَا هِيَ احْتَلَمَتْ فَقَالَ رَسُولُ اللَّهِ صلى الله عليه وسلم ‏\n\"‏ نَعَمْ إِذَا رَأَتِ الْمَاءَ ‏\"‏‏.‏","english":{"narrator":"Narrated Um-Salama:","text":"(the mother of the believers) Um Sulaim, the wife of Abu Talha, came to Allah's Messenger (ﷺ) and said, \"O \nAllah's Messenger (ﷺ)! Verily Allah is not shy of (telling you) the truth. Is it necessary for a woman to take a \nbath after she has a wet dream (nocturnal sexual discharge)?\" Allah's Messenger (ﷺ) replied, \"Yes, if she \nnotices a discharge.\""},"hadithNumber":281,"vol":1,"hadithId":34,"reference":"5:34","meta":{"id":"bukhari","length":7563,"totalChapters":97,"arabic":{"title":"صحيح البخاري","author":"الإمام محمد بن إسماعيل البخاري"},"english":{"title":"Sahih Al Bukhari","author":"Imam Muhammad ibn Ismail al-Bukhari"}},"chapter":{"id":5,"bookId":1,"arabic":"كتاب الغسل","english":"Bathing (Ghusl)","startHadith":248,"endHadith":292,"totalHadiths":45},"version":{"name":"bukhari","title":"Sahih Al Bukhari","chapters":97}}