{"id":143,"idInBook":5001,"chapterId":67,"bookId":1,"arabic":"حَدَّثَنَا عَبْدُ اللَّهِ بْنُ مُحَمَّدِ بْنِ أَسْمَاءَ، حَدَّثَنَا جُوَيْرِيَةُ، عَنْ مَالِكِ بْنِ أَنَسٍ، عَنِ الزُّهْرِيِّ، عَنِ ابْنِ مُحَيْرِيزٍ، عَنْ أَبِي سَعِيدٍ الْخُدْرِيِّ، قَالَ أَصَبْنَا سَبْيًا فَكُنَّا نَعْزِلُ فَسَأَلْنَا رَسُولَ اللَّهِ صلى الله عليه وسلم فَقَالَ ‏\n\"‏ أَوَإِنَّكُمْ لَتَفْعَلُونَ قَالَهَا ثَلاَثًا مَا مِنْ نَسَمَةٍ كَائِنَةٍ إِلَى يَوْمِ الْقِيَامَةِ إِلاَّ هِيَ كَائِنَةٌ ‏\"‏‏.‏","english":{"narrator":"Narrated Abu Sa`id Al-Khudri:","text":"We got female captives in the war booty and we used to do coitus interruptus with them. So we asked \nAllah's Messenger (ﷺ) about it and he said, \"Do you really do that?\" repeating the question thrice, \"There is \nno soul that is destined to exist but will come into existence, till the Day of Resurrection.\""},"hadithNumber":5001,"vol":6,"hadithId":143,"reference":"67:143","meta":{"id":"bukhari","length":7563,"totalChapters":97,"arabic":{"title":"صحيح البخاري","author":"الإمام محمد بن إسماعيل البخاري"},"english":{"title":"Sahih Al Bukhari","author":"Imam Muhammad ibn Ismail al-Bukhari"}},"chapter":{"id":67,"bookId":1,"arabic":"كتاب النكاح","english":"Wedlock, Marriage (Nikaah)","startHadith":4859,"endHadith":5041,"totalHadiths":183},"version":{"name":"bukhari","title":"Sahih Al Bukhari","chapters":97}}