{"id":75,"idInBook":1041,"chapterId":42,"bookId":15,"arabic":"حَدَّثَنَا عَيَّاشُ بْنُ الْوَلِيدِ، قَالَ‏:‏ حَدَّثَنَا عَبْدُ الأَعْلَى، قَالَ‏:‏ حَدَّثَنَا سَعِيدٌ، عَنْ قَتَادَةَ، عَنْ حُمَيْدِ بْنِ هِلاَلٍ، عَنْ عَبْدِ اللهِ بْنِ الصَّامِتِ قَالَ‏:‏ قُلْتُ لأَبِي ذَرٍّ‏:‏ مَرَرْتُ بِعَبْدِ الرَّحْمَنِ بْنِ أُمِّ الْحَكَمِ فَسَلَّمْتُ، فَمَا رَدَّ عَلَيَّ شَيْئًا‏؟‏ فَقَالَ‏:‏ يَا ابْنَ أَخِي، مَا يَكُونُ عَلَيْكَ مِنْ ذَلِكَ‏؟‏ رَدَّ عَلَيْكَ مَنْ هُوَ خَيْرٌ مِنْهُ، مَلَكٌ عَنْ يَمِينِهِ‏.‏","english":{"narrator":"","text":"'Abdullah ibn as-Samit said, \"I said to Abu Dharr, 'I passed by\n'Abdu'r-Rahman ibn Umm al-Hakam and I greeted him and he did not answer\nme at all. He said, 'Nephew, what harm have suffered from that? Someone\nbetter than him answered you ? the angel on his right.\""},"hadithNumber":1041,"hadithId":75,"reference":"42:75","meta":{"id":"aladab_almufrad","length":1326,"totalChapters":57,"arabic":{"title":"الأدب المفرد","author":"الإمام محمد بن إسماعيل البخاري"},"english":{"title":"Al-Adab Al-Mufrad","author":"Imam Muhammad ibn Ismail al-Bukhari"}},"chapter":{"id":42,"bookId":15,"arabic":"كتاب السَّلامِ","english":"Greetings","startHadith":967,"endHadith":1053,"totalHadiths":87},"version":{"name":"aladab_almufrad","title":"Al-Adab Al-Mufrad","chapters":57}}