{"id":17,"idInBook":1301,"chapterId":55,"bookId":15,"arabic":"حَدَّثَنَا مُوسَى، قَالَ‏:‏ حَدَّثَنَا عَبْدُ الْعَزِيزِ قَالَ‏:‏ حَدَّثَنِي شَيْخٌ مِنْ أَهْلِ الْخَيْرِ يُكَنَّى أَبَا عُقْبَةَ قَالَ‏:‏ مَرَرْتُ مَعَ ابْنِ عُمَرَ مَرَّةً بِالطَّرِيقِ، فَمَرَّ بِغِلْمَةٍ مِنَ الْحَبَشِ، فَرَآهُمْ يَلْعَبُونَ، فَأَخْرَجَ دِرْهَمَيْنِ فَأَعْطَاهُمْ‏.‏","english":{"narrator":"","text":"Abu 'Uqba said, \"I once walked along the road with Ibn 'Umar.\nI passed some Abyssinian lads who were playing and he brought out two dirhams\nwhich he gave to them.\""},"hadithNumber":1301,"hadithId":17,"reference":"55:17","meta":{"id":"aladab_almufrad","length":1326,"totalChapters":57,"arabic":{"title":"الأدب المفرد","author":"الإمام محمد بن إسماعيل البخاري"},"english":{"title":"Al-Adab Al-Mufrad","author":"Imam Muhammad ibn Ismail al-Bukhari"}},"chapter":{"id":55,"bookId":15,"arabic":"كتاب المعرفة","english":"Recognition","startHadith":1285,"endHadith":1307,"totalHadiths":23},"version":{"name":"aladab_almufrad","title":"Al-Adab Al-Mufrad","chapters":57}}