{"id":383,"idInBook":562,"chapterId":2,"bookId":17,"arabic":"وَجَابِرِ عِنْدَ أَبِي دَاوُدَ, وَالنَّسَائِيّ ِ  : 1‏ { أَنَّهَا مَا بَيْنَ صَلَاةِ اَلْعَصْرِ إِلَى غُرُوبِ اَلشَّمْسِ }  ِ.‏‏1 ‏- حديث جابر.‏ رواه أبو داود (1048)‏، والنسائي (3/99‏-100)‏ عن رسول الله صلى الله عليه وسلم أنه قال: يوم الجمعة اثنتا عشرة ساعة، لا يوجد فيها عبد مسلم يسأل الله شيئا إلا آتاه إياه، فالتمسوها آخر ساعة بعد العصر\".‏ وهو حديث صحيح، واللفظ للنسائي.‏ \"تنبيه\": قول الحافظ: أنها ما بين صلاة العصر وغروب الشمس.‏ هو تعبير منه بالمعنى، وإلا فليس هذا اللفظ في شيء من روايات الحديث.‏","english":{"narrator":"and Abu Dawud and an-Nasa'i reported from Jabir:","text":"\"It is between the 'Asr prayer and sunset.\""},"hadithNumber":562,"hadithId":383,"reference":"2:383","meta":{"id":"bulugh_almaram","length":1767,"totalChapters":16,"arabic":{"title":"بلوغ المرام","author":"الإمام ابن حجر العسقلاني"},"english":{"title":"Bulugh Al Maram","author":"Ibn Hajar al-Asqalani"}},"chapter":{"id":2,"bookId":17,"arabic":"كتاب الصلاة","english":"The Book of Prayer","startHadith":180,"endHadith":640,"totalHadiths":461},"version":{"name":"bulugh_almaram","title":"Bulugh Al Maram","chapters":16}}